jubeo/__init__.py
jubeo/_print_version.py
jubeo/_version.py
jubeo/cli.py
jubeo/main.py
jubeo/base_repo/.jubeo/jubeo.toml
jubeo/base_repo/.jubeo/requirements.in
jubeo/base_repo/.jubeo/requirements.txt
jubeo/base_repo/tasks/__init__.py
jubeo/base_repo/tasks/config.py
jubeo/base_repo/tasks/sysconfig.py
jubeo/base_repo/tasks/toplevel.py
jubeo/base_repo/tasks/modules/__init__.py
jubeo/base_repo/tasks/modules/core.py
jubeo/base_repo/tasks/modules/core.py~
jubeo/base_repo/tasks/plugins/__init__.py
jubeo/base_repo/tasks/plugins/custom.py
jubeo/config_template/__init__.py
jubeo/config_template/jubeo_conf.toml
jubeo-0.0.3a0.dev0.dist-info/AUTHORS.org
jubeo-0.0.3a0.dev0.dist-info/LICENSE
jubeo-0.0.3a0.dev0.dist-info/METADATA
jubeo-0.0.3a0.dev0.dist-info/WHEEL
jubeo-0.0.3a0.dev0.dist-info/entry_points.txt
jubeo-0.0.3a0.dev0.dist-info/top_level.txt
jubeo-0.0.3a0.dev0.dist-info/RECORD
