Metadata-Version: 2.1
Name: jubeo
Version: 0.0.3a0.dev0
Summary: Small tool for deploying and updating metaproject tooling.
Home-page: https://github.com/salotz/jubeo
Author: Samuel D. Lotz
Author-email: samuel.lotz@salotz.info
License: MIT
Platform: UNKNOWN
Classifier: Topic :: Utilities
Classifier: License :: OSI Approved :: MIT License
Classifier: Programming Language :: Python :: 3
Requires-Dist: gitpython
Requires-Dist: click
Requires-Dist: hyperlink
Requires-Dist: toml
Provides-Extra: all
